lame_nagios_output/__init__.py
lame_nagios_output/nagios_output.py
lame_nagios_output-0.0.1.dist-info/LICENSE
lame_nagios_output-0.0.1.dist-info/METADATA
lame_nagios_output-0.0.1.dist-info/WHEEL
lame_nagios_output-0.0.1.dist-info/top_level.txt
lame_nagios_output-0.0.1.dist-info/RECORD
