Metadata-Version: 2.1
Name: lame-nagios-output
Version: 0.0.1
Summary: simple (and lame) script creating output for Nagios
Home-page: https://github.com/ThomasHoogland/LameNagiosOutput
Author: Thomas Hoogland
Author-email: thoogland@ilionx.com
License: UNKNOWN
Platform: UNKNOWN
Classifier: Programming Language :: Python :: 3
Classifier: License :: OSI Approved :: MIT License
Classifier: Operating System :: OS Independent
Requires-Python: >=3.6
